bodas/__init__.py
bodas/main.py
bodas-0.0.6.dist-info/LICENSE.txt
bodas-0.0.6.dist-info/WHEEL
bodas-0.0.6.dist-info/METADATA
bodas-0.0.6.dist-info/RECORD
